rest_hooks/__init__.py
rest_hooks/admin.py
rest_hooks/client.py
rest_hooks/models.py
rest_hooks/signals.py
rest_hooks/tasks.py
rest_hooks/tests.py
rest_hooks/utils.py
rest_hooks/migrations/0001_initial.py
rest_hooks/migrations/0002_swappable_hook_model.py
rest_hooks/migrations/__init__.py
rest_hooks/south_migrations/0001_initial.py
rest_hooks/south_migrations/__init__.py
django_rest_hooks_tmp-1.6.1.dist-info/AUTHORS.md
django_rest_hooks_tmp-1.6.1.dist-info/LICENSE.md
django_rest_hooks_tmp-1.6.1.dist-info/METADATA
django_rest_hooks_tmp-1.6.1.dist-info/WHEEL
django_rest_hooks_tmp-1.6.1.dist-info/top_level.txt
django_rest_hooks_tmp-1.6.1.dist-info/RECORD
